wplay/__init__.py
wplay/__main__.py
wplay/about_changer.py
wplay/broadcast_message.py
wplay/chat_intermediator.py
wplay/chatbot.py
wplay/download_media.py
wplay/get_media.py
wplay/get_news.py
wplay/message_blast.py
wplay/message_service.py
wplay/message_timer.py
wplay/online_tracker.py
wplay/profile_download.py
wplay/save_chat.py
wplay/schedule_message.py
wplay/target_info.py
wplay/telegram_bot.py
wplay/terminal_chat.py
wplay/text_to_speech.py
wplay/utils/Logger.py
wplay/utils/MessageStack.py
wplay/utils/SessionManager.py
wplay/utils/__init__.py
wplay/utils/browser_config.py
wplay/utils/helpers.py
wplay/utils/io.py
wplay/utils/target_data.py
wplay/utils/target_search.py
wplay/utils/target_select.py
wplay/utils/verify_internet.py
wplay-8.0.7.dist-info/LICENSE
wplay-8.0.7.dist-info/METADATA
wplay-8.0.7.dist-info/WHEEL
wplay-8.0.7.dist-info/entry_points.txt
wplay-8.0.7.dist-info/top_level.txt
wplay-8.0.7.dist-info/RECORD
