Metadata-Version: 2.1
Name: wplay
Version: 8.0.7
Summary: command line software to play with your WhatsApp
Home-page: https://github.com/rpotter12/whatsapp-play/
Author: Rohit Potter, Alexandre Calil
Author-email: rohitpotter12@gmail.com, alexandrecalilmf@gmail.com
License: MIT
Download-URL: https://pypi.org/project/wplay/
Keywords: whatsapp,whatsapp cli,whatsapp api,whatsapp servicewhatsapp chat,message blast,message timer,whatsapp terminal,whatsapp news,whatsapp schedule,tracker,online tracking,save-chat
Platform: UNKNOWN
Classifier: Programming Language :: Python
Classifier: Programming Language :: Python :: 3
Classifier: Programming Language :: Python :: 3.6
Classifier: Programming Language :: Python :: 3.7
Classifier: Programming Language :: Python :: 3.8
Classifier: Programming Language :: Python :: 3 :: Only
Classifier: License :: OSI Approved :: MIT License
Classifier: Operating System :: OS Independent
Requires-Python: >=3.6
Requires-Dist: argparse (>=1.4.0)
Requires-Dist: beautifulsoup4 (>=4.8.1)
Requires-Dist: colorama (>=0.4.3)
Requires-Dist: dateTime (>=4.3)
Requires-Dist: decorator (>=4.4.2)
Requires-Dist: flake8 (>=3.7.9)
Requires-Dist: google (>=2.0.3)
Requires-Dist: gTTS (==2.1.1)
Requires-Dist: newsapi-python (>=0.2.6)
Requires-Dist: phonenumbers (==8.10.2)
Requires-Dist: playsound (>=1.2.2)
Requires-Dist: prompt-toolkit (==1.0.14)
Requires-Dist: psutil (>=5.7.0)
Requires-Dist: pyfiglet (>=0.8.post1)
Requires-Dist: pyflakes (>=2.2.0)
Requires-Dist: Pygments (>=2.6.1)
Requires-Dist: pyppeteer (>=0.0.25)
Requires-Dist: python-dotenv (==0.12.0)
Requires-Dist: python-telegram-bot (>=11.1.0)
Requires-Dist: requests (>=2.22.0)
Requires-Dist: transitions (>=0.7.2)
Requires-Dist: urllib3 (>=1.25.8)
Requires-Dist: websockets (>=8.1)
Requires-Dist: whaaaaat (>=0.5.2)
